calculate_functions/__init__.py
calculate_functions/functions.py
tests/__init__.py
tests/test_functions.py
calculate_functions-0.1.0.dist-info/LICENSE
calculate_functions-0.1.0.dist-info/METADATA
calculate_functions-0.1.0.dist-info/WHEEL
calculate_functions-0.1.0.dist-info/top_level.txt
calculate_functions-0.1.0.dist-info/RECORD
