Metadata-Version: 2.1
Name: calculate_functions
Version: 0.1.0
Summary: A sample Python library
Home-page: 
Author: shivajiwankhede
Author-email: shivaji.wankhede@gmail.com
Classifier: Programming Language :: Python :: 3
Classifier: License :: OSI Approved :: Python Software Foundation License
Classifier: Operating System :: OS Independent
Requires-Python: >=3.6
License-File: LICENSE
